trackfilter/__init__.py
trackfilter/__main__.py
trackfilter/cli.py
trackfilter-1.2.0.dist-info/AUTHORS.rst
trackfilter-1.2.0.dist-info/METADATA
trackfilter-1.2.0.dist-info/WHEEL
trackfilter-1.2.0.dist-info/entry_points.txt
trackfilter-1.2.0.dist-info/top_level.txt
trackfilter-1.2.0.dist-info/RECORD
