Metadata-Version: 2.1
Name: trackfilter
Version: 1.2.0
Summary: Remove YouTube-related garbage from song titles.
Home-page: https://github.com/mirrorfm/trackfilter
Author: Stephane Bruckert
Author-email: stephane.bruckert@gmail.com
License: MIT
Project-URL: Documentation, https://trackfilter.readthedocs.io/
Project-URL: Changelog, https://trackfilter.readthedocs.io/en/latest/changelog.html
Project-URL: Issue Tracker, https://github.com/mirrorfm/trackfilter/issues
Requires-Python: ~=3.8
License-File: AUTHORS.rst
